nlp_sentiment/__init__.py
nlp_sentiment/main.py
NLP_sentiment-2.0.0.dist-info/METADATA
NLP_sentiment-2.0.0.dist-info/WHEEL
NLP_sentiment-2.0.0.dist-info/top_level.txt
NLP_sentiment-2.0.0.dist-info/RECORD
