Metadata-Version: 2.1
Name: NLP-sentiment
Version: 2.0.0
Requires-Dist: numpy >=1.26.3
